pymalts2/__init__.py
pymalts2-0.0.2.dist-info/LICENSE
pymalts2-0.0.2.dist-info/METADATA
pymalts2-0.0.2.dist-info/WHEEL
pymalts2-0.0.2.dist-info/top_level.txt
pymalts2-0.0.2.dist-info/RECORD
