Metadata-Version: 2.1
Name: pymalts2
Version: 0.0.2
Summary: Causal Inference Matching Package.
Home-page: https://github.com/almost-matching-exactly/MALTS
Author: Harsh Parikh
Author-email: harsh.parikh@duke.edu
License: UNKNOWN
Platform: UNKNOWN
Classifier: Programming Language :: Python :: 3
Classifier: License :: OSI Approved :: MIT License
Classifier: Operating System :: OS Independent
Requires-Python: >=3.6
